main.py
calcot-0.1.0.dist-info/METADATA
calcot-0.1.0.dist-info/WHEEL
calcot-0.1.0.dist-info/top_level.txt
calcot-0.1.0.dist-info/RECORD
