Metadata-Version: 2.4
Name: calcot
Version: 0.1.0
Summary: Calçot: a smoky parody of Celery 🧅🔥
Requires-Python: >=3.13
